tests
dedun
