Metadata-Version: 1.0
Name: dedun
Version: 0.3.2
Summary: Dedun is a Python client for the RESTful API of API.Leipzig. This API gives access to the public data of the city of Leipzig.
Home-page: https://bitbucket.org/keimlink/dedun
Author: Markus Zapke-Gründemann
Author-email: info@keimlink.de
License: BSD License
Platform: UNKNOWN
Classifier: Development Status :: 4 - Beta
Classifier: Environment :: Web Environment
Classifier: Intended Audience :: Developers
Classifier: License :: OSI Approved :: BSD License
Classifier: Operating System :: OS Independent
Classifier: Programming Language :: Python
Classifier: Topic :: Internet :: WWW/HTTP
Classifier: Topic :: Software Development :: Libraries
